{
  "vaultName": "Fluid Mechanics",
  "lastExport": 1725447282939,
  "pluginVersion": "1.8.01",
  "validBodyClasses": "publish css-settings-manager theme-dark show-inline-title show-ribbon",
  "useCustomHeadContent": true,
  "useCustomFavicon": false,
  "files": [
    "2024-08-07.md",
    "accentric factor.md",
    "Accounting.md",
    "Accounts quiz 1.md",
    "Agastya's solution.md",
    "Agastya'sproblem.canvas",
    "Astral.md",
    "Atomic spectroscopy methods.md",
    "Basics of reactors.md",
    "Bernoulli's Equation.md",
    "Bhopal Accident.md",
    "Bio-safety.md",
    "Calculator.md",
    "Chemical Reaction Engineering.md",
    "Chromatographic methods.md",
    "CHT 1013.md",
    "Conduction.md",
    "Convection.md",
    "Density.md",
    "distribution.md",
    "doubt session.md",
    "Economics.md",
    "Electrical Safety.md",
    "Electroanalytical methods.md",
    "Engineering thermodynamics.md",
    "Enthalpy Accumulation.md",
    "Entropy.md",
    "Environmental Science.md",
    "EOS.md",
    "exergy special.md",
    "Experimental Kinetics.md",
    "Explaining the Economy.md",
    "Fire Safety.md",
    "Fluid mechanics.md",
    "Fluid Moving Machinery.md",
    "Fluid Statics.md",
    "Fourier's Law.md",
    "functionality.md",
    "Garware Hitech.md",
    "Gas cylinder safety.md",
    "gibbs free energy.md",
    "Heat Transfer.md",
    "Index.md",
    "Industry.md",
    "Intro to chemical analysis.md",
    "Intro to heterogeneous reactions.md",
    "Kinetics Homogeneous.md",
    "Lab safety.md",
    "Lec 8.md",
    "Linear Polymers.md",
    "Linear Step Polymerization.md",
    "Machine Safety.md",
    "Mixing.md",
    "Molar Mass.md",
    "Molecular spectroscopy.md",
    "MSDS and PPE.md",
    "Non ideal flow.md",
    "Pasted image 20240620105944.png",
    "Pasted image 20240621004336.png",
    "Pasted image 20240621202105.png",
    "Pasted image 20240621202300.png",
    "Pasted image 20240621225105.png",
    "Pasted image 20240621235412.png",
    "Pasted image 20240621235423.png",
    "Pasted image 20240621235442.png",
    "Pasted image 20240622173336.png",
    "Pasted image 20240622184349.png",
    "Pasted image 20240626172127.png",
    "Pasted image 20240627122402.png",
    "Pasted image 20240701113218.png",
    "Pasted image 20240701113320.png",
    "Pasted image 20240701113546.png",
    "Pasted image 20240701113614.png",
    "Pasted image 20240701114143.png",
    "Pasted image 20240701115336.png",
    "Pasted image 20240701115810.png",
    "Pasted image 20240701121329.png",
    "Pasted image 20240703111509.png",
    "Pasted image 20240704093411.png",
    "Pasted image 20240704093611.png",
    "Pasted image 20240704094056.png",
    "Pasted image 20240704102602.png",
    "Pasted image 20240704105532.png",
    "Pasted image 20240704105544.png",
    "Pasted image 20240712161013.png",
    "Pasted image 20240712161207.png",
    "Pasted image 20240713172639.png",
    "Pasted image 20240714152942.png",
    "Pasted image 20240714152959.png",
    "Pasted image 20240714153112.png",
    "Pasted image 20240714153200.png",
    "Pasted image 20240716110652.png",
    "Pasted image 20240716110730.png",
    "Pasted image 20240716111108.png",
    "Pasted image 20240718105744.png",
    "Pasted image 20240718123151.png",
    "Pasted image 20240723105856.png",
    "Pasted image 20240723115032.png",
    "Pasted image 20240723120502.png",
    "Pasted image 20240731101144.png",
    "Pasted image 20240731105552.png",
    "Pasted image 20240802100231.png",
    "Pasted image 20240802100254.png",
    "Pasted image 20240807101118.png",
    "Pasted image 20240807104503.png",
    "Pasted image 20240807221038.png",
    "Pasted image 20240807221419.png",
    "Pasted image 20240808143749.png",
    "Pasted image 20240808154935.png",
    "Pasted image 20240809214724.png",
    "Pasted image 20240813081657.png",
    "Pasted image 20240814163039.png",
    "Pasted image 20240821111415.png",
    "Pasted image 20240821111418.png",
    "Pasted image 20240822065437.png",
    "Pasted image 20240822071834.png",
    "Pasted image 20240823094343.png",
    "Polyesters.md",
    "Polymerization.md",
    "Polymers.md",
    "Process safety.md",
    "Processing.md",
    "Real Gases.md",
    "Selection of analytical methods.md",
    "Shaily.md",
    "solution to question 1.md",
    "Statistics problems.md",
    "step growth.md",
    "Supreme Industries.md",
    "Takshil's Problem.md",
    "Types of polymers.md",
    "Unsteady Heat Conduction.md",
    "Volume.md",
    "Water Pollution.md",
    "lib/fonts/94f2f163d4b698242fef.otf",
    "lib/fonts/72505e6a122c6acd5471.woff2",
    "lib/fonts/2d5198822ab091ce4305.woff2",
    "lib/fonts/c8ba52b05a9ef10f4758.woff2",
    "lib/fonts/cb10ffd7684cd9836a05.woff2",
    "lib/fonts/b5f0f109bc88052d4000.woff2",
    "lib/fonts/cbe0ae49c52c920fd563.woff2",
    "lib/fonts/535a6cf662596b3bd6a6.woff2",
    "lib/fonts/70cc7ff27245e82ad414.ttf",
    "lib/fonts/454577c22304619db035.ttf",
    "lib/fonts/52ac8f3034507f1d9e53.ttf",
    "lib/fonts/05b618077343fbbd92b7.ttf",
    "lib/fonts/4bb6ac751d1c5478ff3a.woff2",
    "lib/media/874d8b8e340f75575caa.svg",
    "lib/media/3d6c1bdc4d87cde4de67.svg",
    "lib/fonts/MathJax_Zero.woff",
    "lib/fonts/MathJax_Main-Regular.woff",
    "lib/fonts/MathJax_Main-Bold.woff",
    "lib/fonts/MathJax_Math-Italic.woff",
    "lib/fonts/MathJax_Main-Italic.woff",
    "lib/fonts/MathJax_Math-BoldItalic.woff",
    "lib/fonts/MathJax_Size1-Regular.woff",
    "lib/fonts/MathJax_Size2-Regular.woff",
    "lib/fonts/MathJax_Size3-Regular.woff",
    "lib/fonts/MathJax_Size4-Regular.woff",
    "lib/fonts/MathJax_AMS-Regular.woff",
    "lib/fonts/MathJax_Calligraphic-Regular.woff",
    "lib/fonts/MathJax_Calligraphic-Bold.woff",
    "lib/fonts/MathJax_Fraktur-Regular.woff",
    "lib/fonts/MathJax_Fraktur-Bold.woff",
    "lib/fonts/MathJax_SansSerif-Regular.woff",
    "lib/fonts/MathJax_SansSerif-Bold.woff",
    "lib/fonts/MathJax_SansSerif-Italic.woff",
    "lib/fonts/MathJax_Script-Regular.woff",
    "lib/fonts/MathJax_Typewriter-Regular.woff",
    "lib/fonts/MathJax_Vector-Regular.woff",
    "lib/fonts/MathJax_Vector-Bold.woff"
  ],
  "mainDependencies": [
    "lib/fonts/94f2f163d4b698242fef.otf",
    "lib/fonts/72505e6a122c6acd5471.woff2",
    "lib/fonts/2d5198822ab091ce4305.woff2",
    "lib/fonts/c8ba52b05a9ef10f4758.woff2",
    "lib/fonts/cb10ffd7684cd9836a05.woff2",
    "lib/fonts/b5f0f109bc88052d4000.woff2",
    "lib/fonts/cbe0ae49c52c920fd563.woff2",
    "lib/fonts/535a6cf662596b3bd6a6.woff2",
    "lib/fonts/70cc7ff27245e82ad414.ttf",
    "lib/fonts/454577c22304619db035.ttf",
    "lib/fonts/52ac8f3034507f1d9e53.ttf",
    "lib/fonts/05b618077343fbbd92b7.ttf",
    "lib/fonts/4bb6ac751d1c5478ff3a.woff2",
    "lib/media/874d8b8e340f75575caa.svg",
    "lib/media/3d6c1bdc4d87cde4de67.svg",
    "lib/fonts/MathJax_Zero.woff",
    "lib/fonts/MathJax_Main-Regular.woff",
    "lib/fonts/MathJax_Main-Bold.woff",
    "lib/fonts/MathJax_Math-Italic.woff",
    "lib/fonts/MathJax_Main-Italic.woff",
    "lib/fonts/MathJax_Math-BoldItalic.woff",
    "lib/fonts/MathJax_Size1-Regular.woff",
    "lib/fonts/MathJax_Size2-Regular.woff",
    "lib/fonts/MathJax_Size3-Regular.woff",
    "lib/fonts/MathJax_Size4-Regular.woff",
    "lib/fonts/MathJax_AMS-Regular.woff",
    "lib/fonts/MathJax_Calligraphic-Regular.woff",
    "lib/fonts/MathJax_Calligraphic-Bold.woff",
    "lib/fonts/MathJax_Fraktur-Regular.woff",
    "lib/fonts/MathJax_Fraktur-Bold.woff",
    "lib/fonts/MathJax_SansSerif-Regular.woff",
    "lib/fonts/MathJax_SansSerif-Bold.woff",
    "lib/fonts/MathJax_SansSerif-Italic.woff",
    "lib/fonts/MathJax_Script-Regular.woff",
    "lib/fonts/MathJax_Typewriter-Regular.woff",
    "lib/fonts/MathJax_Vector-Regular.woff",
    "lib/fonts/MathJax_Vector-Bold.woff"
  ],
  "fileInfo": {
    "lib/fonts/94f2f163d4b698242fef.otf": {
      "modifiedTime": 1725447282939,
      "sourceSize": 66800,
      "exportedPath": "lib/fonts/94f2f163d4b698242fef.otf",
      "dependencies": []
    },
    "lib/fonts/72505e6a122c6acd5471.woff2": {
      "modifiedTime": 1725447282939,
      "sourceSize": 104232,
      "exportedPath": "lib/fonts/72505e6a122c6acd5471.woff2",
      "dependencies": []
    },
    "lib/fonts/2d5198822ab091ce4305.woff2": {
      "modifiedTime": 1725447282939,
      "sourceSize": 104332,
      "exportedPath": "lib/fonts/2d5198822ab091ce4305.woff2",
      "dependencies": []
    },
    "lib/fonts/c8ba52b05a9ef10f4758.woff2": {
      "modifiedTime": 1725447282939,
      "sourceSize": 98868,
      "exportedPath": "lib/fonts/c8ba52b05a9ef10f4758.woff2",
      "dependencies": []
    },
    "lib/fonts/cb10ffd7684cd9836a05.woff2": {
      "modifiedTime": 1725447282939,
      "sourceSize": 106876,
      "exportedPath": "lib/fonts/cb10ffd7684cd9836a05.woff2",
      "dependencies": []
    },
    "lib/fonts/b5f0f109bc88052d4000.woff2": {
      "modifiedTime": 1725447282939,
      "sourceSize": 105804,
      "exportedPath": "lib/fonts/b5f0f109bc88052d4000.woff2",
      "dependencies": []
    },
    "lib/fonts/cbe0ae49c52c920fd563.woff2": {
      "modifiedTime": 1725447282939,
      "sourceSize": 106108,
      "exportedPath": "lib/fonts/cbe0ae49c52c920fd563.woff2",
      "dependencies": []
    },
    "lib/fonts/535a6cf662596b3bd6a6.woff2": {
      "modifiedTime": 1725447282939,
      "sourceSize": 111708,
      "exportedPath": "lib/fonts/535a6cf662596b3bd6a6.woff2",
      "dependencies": []
    },
    "lib/fonts/70cc7ff27245e82ad414.ttf": {
      "modifiedTime": 1725447282939,
      "sourceSize": 192740,
      "exportedPath": "lib/fonts/70cc7ff27245e82ad414.ttf",
      "dependencies": []
    },
    "lib/fonts/454577c22304619db035.ttf": {
      "modifiedTime": 1725447282939,
      "sourceSize": 161376,
      "exportedPath": "lib/fonts/454577c22304619db035.ttf",
      "dependencies": []
    },
    "lib/fonts/52ac8f3034507f1d9e53.ttf": {
      "modifiedTime": 1725447282939,
      "sourceSize": 191568,
      "exportedPath": "lib/fonts/52ac8f3034507f1d9e53.ttf",
      "dependencies": []
    },
    "lib/fonts/05b618077343fbbd92b7.ttf": {
      "modifiedTime": 1725447282939,
      "sourceSize": 155288,
      "exportedPath": "lib/fonts/05b618077343fbbd92b7.ttf",
      "dependencies": []
    },
    "lib/fonts/4bb6ac751d1c5478ff3a.woff2": {
      "modifiedTime": 1725447282939,
      "sourceSize": 7876,
      "exportedPath": "lib/fonts/4bb6ac751d1c5478ff3a.woff2",
      "dependencies": []
    },
    "lib/media/874d8b8e340f75575caa.svg": {
      "modifiedTime": 1725447282939,
      "sourceSize": 317,
      "exportedPath": "lib/media/874d8b8e340f75575caa.svg",
      "dependencies": []
    },
    "lib/media/3d6c1bdc4d87cde4de67.svg": {
      "modifiedTime": 1725447282939,
      "sourceSize": 279,
      "exportedPath": "lib/media/3d6c1bdc4d87cde4de67.svg",
      "dependencies": []
    },
    "lib/fonts/MathJax_Zero.woff": {
      "modifiedTime": 1725447282939,
      "sourceSize": 1368,
      "exportedPath": "lib/fonts/MathJax_Zero.woff",
      "dependencies": []
    },
    "lib/fonts/MathJax_Main-Regular.woff": {
      "modifiedTime": 1725447282939,
      "sourceSize": 34160,
      "exportedPath": "lib/fonts/MathJax_Main-Regular.woff",
      "dependencies": []
    },
    "lib/fonts/MathJax_Main-Bold.woff": {
      "modifiedTime": 1725447282939,
      "sourceSize": 34464,
      "exportedPath": "lib/fonts/MathJax_Main-Bold.woff",
      "dependencies": []
    },
    "lib/fonts/MathJax_Math-Italic.woff": {
      "modifiedTime": 1725447282939,
      "sourceSize": 19360,
      "exportedPath": "lib/fonts/MathJax_Math-Italic.woff",
      "dependencies": []
    },
    "lib/fonts/MathJax_Main-Italic.woff": {
      "modifiedTime": 1725447282939,
      "sourceSize": 20832,
      "exportedPath": "lib/fonts/MathJax_Main-Italic.woff",
      "dependencies": []
    },
    "lib/fonts/MathJax_Math-BoldItalic.woff": {
      "modifiedTime": 1725447282939,
      "sourceSize": 19776,
      "exportedPath": "lib/fonts/MathJax_Math-BoldItalic.woff",
      "dependencies": []
    },
    "lib/fonts/MathJax_Size1-Regular.woff": {
      "modifiedTime": 1725447282939,
      "sourceSize": 5792,
      "exportedPath": "lib/fonts/MathJax_Size1-Regular.woff",
      "dependencies": []
    },
    "lib/fonts/MathJax_Size2-Regular.woff": {
      "modifiedTime": 1725447282939,
      "sourceSize": 5464,
      "exportedPath": "lib/fonts/MathJax_Size2-Regular.woff",
      "dependencies": []
    },
    "lib/fonts/MathJax_Size3-Regular.woff": {
      "modifiedTime": 1725447282939,
      "sourceSize": 3244,
      "exportedPath": "lib/fonts/MathJax_Size3-Regular.woff",
      "dependencies": []
    },
    "lib/fonts/MathJax_Size4-Regular.woff": {
      "modifiedTime": 1725447282939,
      "sourceSize": 5148,
      "exportedPath": "lib/fonts/MathJax_Size4-Regular.woff",
      "dependencies": []
    },
    "lib/fonts/MathJax_AMS-Regular.woff": {
      "modifiedTime": 1725447282939,
      "sourceSize": 40808,
      "exportedPath": "lib/fonts/MathJax_AMS-Regular.woff",
      "dependencies": []
    },
    "lib/fonts/MathJax_Calligraphic-Regular.woff": {
      "modifiedTime": 1725447282939,
      "sourceSize": 9600,
      "exportedPath": "lib/fonts/MathJax_Calligraphic-Regular.woff",
      "dependencies": []
    },
    "lib/fonts/MathJax_Calligraphic-Bold.woff": {
      "modifiedTime": 1725447282939,
      "sourceSize": 9908,
      "exportedPath": "lib/fonts/MathJax_Calligraphic-Bold.woff",
      "dependencies": []
    },
    "lib/fonts/MathJax_Fraktur-Regular.woff": {
      "modifiedTime": 1725447282939,
      "sourceSize": 21480,
      "exportedPath": "lib/fonts/MathJax_Fraktur-Regular.woff",
      "dependencies": []
    },
    "lib/fonts/MathJax_Fraktur-Bold.woff": {
      "modifiedTime": 1725447282939,
      "sourceSize": 22340,
      "exportedPath": "lib/fonts/MathJax_Fraktur-Bold.woff",
      "dependencies": []
    },
    "lib/fonts/MathJax_SansSerif-Regular.woff": {
      "modifiedTime": 1725447282939,
      "sourceSize": 12660,
      "exportedPath": "lib/fonts/MathJax_SansSerif-Regular.woff",
      "dependencies": []
    },
    "lib/fonts/MathJax_SansSerif-Bold.woff": {
      "modifiedTime": 1725447282939,
      "sourceSize": 15944,
      "exportedPath": "lib/fonts/MathJax_SansSerif-Bold.woff",
      "dependencies": []
    },
    "lib/fonts/MathJax_SansSerif-Italic.woff": {
      "modifiedTime": 1725447282939,
      "sourceSize": 14628,
      "exportedPath": "lib/fonts/MathJax_SansSerif-Italic.woff",
      "dependencies": []
    },
    "lib/fonts/MathJax_Script-Regular.woff": {
      "modifiedTime": 1725447282939,
      "sourceSize": 11852,
      "exportedPath": "lib/fonts/MathJax_Script-Regular.woff",
      "dependencies": []
    },
    "lib/fonts/MathJax_Typewriter-Regular.woff": {
      "modifiedTime": 1725447282939,
      "sourceSize": 17604,
      "exportedPath": "lib/fonts/MathJax_Typewriter-Regular.woff",
      "dependencies": []
    },
    "lib/fonts/MathJax_Vector-Regular.woff": {
      "modifiedTime": 1725447282939,
      "sourceSize": 1136,
      "exportedPath": "lib/fonts/MathJax_Vector-Regular.woff",
      "dependencies": []
    },
    "lib/fonts/MathJax_Vector-Bold.woff": {
      "modifiedTime": 1725447282939,
      "sourceSize": 1116,
      "exportedPath": "lib/fonts/MathJax_Vector-Bold.woff",
      "dependencies": []
    },
    "Index.md": {
      "modifiedTime": 1725447282939,
      "sourceSize": 1142,
      "exportedPath": "Index.html",
      "dependencies": []
    },
    "2024-08-07.md": {
      "modifiedTime": 1725447282939,
      "sourceSize": 18,
      "exportedPath": "2024-08-07.html",
      "dependencies": []
    },
    "accentric factor.md": {
      "modifiedTime": 1725447282939,
      "sourceSize": 147,
      "exportedPath": "accentric factor.html",
      "dependencies": []
    },
    "Accounting.md": {
      "modifiedTime": 1725447282939,
      "sourceSize": 13771,
      "exportedPath": "Accounting.html",
      "dependencies": []
    },
    "Agastya's solution.md": {
      "modifiedTime": 1725447282939,
      "sourceSize": 3952,
      "exportedPath": "Agastya's solution.html",
      "dependencies": []
    },
    "Agastya'sproblem.canvas": {
      "modifiedTime": 1725447282939,
      "sourceSize": 1130,
      "exportedPath": "Agastya'sproblem.html",
      "dependencies": []
    },
    "Astral.md": {
      "modifiedTime": 1725447282939,
      "sourceSize": 2913,
      "exportedPath": "Astral.html",
      "dependencies": []
    },
    "Atomic spectroscopy methods.md": {
      "modifiedTime": 1725447282939,
      "sourceSize": 142,
      "exportedPath": "Atomic spectroscopy methods.html",
      "dependencies": []
    },
    "Basics of reactors.md": {
      "modifiedTime": 1725447282939,
      "sourceSize": 856,
      "exportedPath": "Basics of reactors.html",
      "dependencies": []
    },
    "Bernoulli's Equation.md": {
      "modifiedTime": 1725447282939,
      "sourceSize": 13843,
      "exportedPath": "Bernoulli's Equation.html",
      "dependencies": []
    },
    "Bhopal Accident.md": {
      "modifiedTime": 1725447282939,
      "sourceSize": 3339,
      "exportedPath": "Bhopal Accident.html",
      "dependencies": []
    },
    "Bio-safety.md": {
      "modifiedTime": 1725447282939,
      "sourceSize": 1686,
      "exportedPath": "Bio-safety.html",
      "dependencies": []
    },
    "Calculator.md": {
      "modifiedTime": 1725447282939,
      "sourceSize": 396,
      "exportedPath": "Calculator.html",
      "dependencies": []
    },
    "Chemical Reaction Engineering.md": {
      "modifiedTime": 1725447282939,
      "sourceSize": 459,
      "exportedPath": "Chemical Reaction Engineering.html",
      "dependencies": []
    },
    "Chromatographic methods.md": {
      "modifiedTime": 1725447282939,
      "sourceSize": 1510,
      "exportedPath": "Chromatographic methods.html",
      "dependencies": []
    },
    "CHT 1013.md": {
      "modifiedTime": 1725447282939,
      "sourceSize": 462,
      "exportedPath": "CHT 1013.html",
      "dependencies": []
    },
    "Conduction.md": {
      "modifiedTime": 1725447282939,
      "sourceSize": 345,
      "exportedPath": "Conduction.html",
      "dependencies": []
    },
    "Convection.md": {
      "modifiedTime": 1725447282939,
      "sourceSize": 377,
      "exportedPath": "Convection.html",
      "dependencies": []
    },
    "Density.md": {
      "modifiedTime": 1725447282939,
      "sourceSize": 721,
      "exportedPath": "Density.html",
      "dependencies": []
    },
    "distribution.md": {
      "modifiedTime": 1725447282939,
      "sourceSize": 103,
      "exportedPath": "distribution.html",
      "dependencies": []
    },
    "doubt session.md": {
      "modifiedTime": 1725447282939,
      "sourceSize": 1028,
      "exportedPath": "doubt session.html",
      "dependencies": []
    },
    "Economics.md": {
      "modifiedTime": 1725447282939,
      "sourceSize": 51,
      "exportedPath": "Economics.html",
      "dependencies": []
    },
    "Electrical Safety.md": {
      "modifiedTime": 1725447282939,
      "sourceSize": 1824,
      "exportedPath": "Electrical Safety.html",
      "dependencies": []
    },
    "Electroanalytical methods.md": {
      "modifiedTime": 1725447282939,
      "sourceSize": 260,
      "exportedPath": "Electroanalytical methods.html",
      "dependencies": []
    },
    "Engineering thermodynamics.md": {
      "modifiedTime": 1725447282939,
      "sourceSize": 701,
      "exportedPath": "Engineering thermodynamics.html",
      "dependencies": []
    },
    "Enthalpy Accumulation.md": {
      "modifiedTime": 1725447282939,
      "sourceSize": 2004,
      "exportedPath": "Enthalpy Accumulation.html",
      "dependencies": []
    },
    "Entropy.md": {
      "modifiedTime": 1725447282939,
      "sourceSize": 3248,
      "exportedPath": "Entropy.html",
      "dependencies": []
    },
    "Environmental Science.md": {
      "modifiedTime": 1725447282939,
      "sourceSize": 3059,
      "exportedPath": "Environmental Science.html",
      "dependencies": []
    },
    "EOS.md": {
      "modifiedTime": 1725447282939,
      "sourceSize": 6087,
      "exportedPath": "EOS.html",
      "dependencies": []
    },
    "exergy special.md": {
      "modifiedTime": 1725447282939,
      "sourceSize": 731,
      "exportedPath": "exergy special.html",
      "dependencies": []
    },
    "Experimental Kinetics.md": {
      "modifiedTime": 1725447282939,
      "sourceSize": 476,
      "exportedPath": "Experimental Kinetics.html",
      "dependencies": []
    },
    "Explaining the Economy.md": {
      "modifiedTime": 1725447282939,
      "sourceSize": 37,
      "exportedPath": "Explaining the Economy.html",
      "dependencies": []
    },
    "Fire Safety.md": {
      "modifiedTime": 1725447282939,
      "sourceSize": 2315,
      "exportedPath": "Fire Safety.html",
      "dependencies": []
    },
    "Fluid mechanics.md": {
      "modifiedTime": 1725447282939,
      "sourceSize": 1346,
      "exportedPath": "Fluid mechanics.html",
      "dependencies": []
    },
    "Fluid Moving Machinery.md": {
      "modifiedTime": 1725447282939,
      "sourceSize": 4274,
      "exportedPath": "Fluid Moving Machinery.html",
      "dependencies": []
    },
    "Fluid Statics.md": {
      "modifiedTime": 1725447282939,
      "sourceSize": 1195,
      "exportedPath": "Fluid Statics.html",
      "dependencies": []
    },
    "Fourier's Law.md": {
      "modifiedTime": 1725447282939,
      "sourceSize": 1910,
      "exportedPath": "Fourier's Law.html",
      "dependencies": []
    },
    "functionality.md": {
      "modifiedTime": 1725447282939,
      "sourceSize": 334,
      "exportedPath": "functionality.html",
      "dependencies": []
    },
    "Gas cylinder safety.md": {
      "modifiedTime": 1725447282939,
      "sourceSize": 1310,
      "exportedPath": "Gas cylinder safety.html",
      "dependencies": []
    },
    "gibbs free energy.md": {
      "modifiedTime": 1725447282939,
      "sourceSize": 4317,
      "exportedPath": "gibbs free energy.html",
      "dependencies": []
    },
    "Heat Transfer.md": {
      "modifiedTime": 1725447282939,
      "sourceSize": 1031,
      "exportedPath": "Heat Transfer.html",
      "dependencies": []
    },
    "Industry.md": {
      "modifiedTime": 1725447282939,
      "sourceSize": 983,
      "exportedPath": "Industry.html",
      "dependencies": []
    },
    "Intro to chemical analysis.md": {
      "modifiedTime": 1725447282939,
      "sourceSize": 3492,
      "exportedPath": "Intro to chemical analysis.html",
      "dependencies": []
    },
    "Intro to heterogeneous reactions.md": {
      "modifiedTime": 1725447282939,
      "sourceSize": 531,
      "exportedPath": "Intro to heterogeneous reactions.html",
      "dependencies": []
    },
    "Kinetics Homogeneous.md": {
      "modifiedTime": 1725447282939,
      "sourceSize": 734,
      "exportedPath": "Kinetics Homogeneous.html",
      "dependencies": []
    },
    "Lab safety.md": {
      "modifiedTime": 1725447282939,
      "sourceSize": 3667,
      "exportedPath": "Lab safety.html",
      "dependencies": []
    },
    "Linear Polymers.md": {
      "modifiedTime": 1725447282939,
      "sourceSize": 530,
      "exportedPath": "Linear Polymers.html",
      "dependencies": []
    },
    "Linear Step Polymerization.md": {
      "modifiedTime": 1725447282939,
      "sourceSize": 2714,
      "exportedPath": "Linear Step Polymerization.html",
      "dependencies": []
    },
    "Machine Safety.md": {
      "modifiedTime": 1725447282939,
      "sourceSize": 3944,
      "exportedPath": "Machine Safety.html",
      "dependencies": []
    },
    "Mixing.md": {
      "modifiedTime": 1725447282939,
      "sourceSize": 629,
      "exportedPath": "Mixing.html",
      "dependencies": []
    },
    "Molar Mass.md": {
      "modifiedTime": 1725447282939,
      "sourceSize": 799,
      "exportedPath": "Molar Mass.html",
      "dependencies": []
    },
    "Molecular spectroscopy.md": {
      "modifiedTime": 1725447282939,
      "sourceSize": 297,
      "exportedPath": "Molecular spectroscopy.html",
      "dependencies": []
    },
    "MSDS and PPE.md": {
      "modifiedTime": 1725447282939,
      "sourceSize": 2113,
      "exportedPath": "MSDS and PPE.html",
      "dependencies": []
    },
    "Non ideal flow.md": {
      "modifiedTime": 1725447282939,
      "sourceSize": 4211,
      "exportedPath": "Non ideal flow.html",
      "dependencies": []
    },
    "Pasted image 20240620105944.png": {
      "modifiedTime": 1725447282939,
      "sourceSize": 20670,
      "exportedPath": "Pasted image 20240620105944.png",
      "dependencies": []
    },
    "Pasted image 20240621004336.png": {
      "modifiedTime": 1725447282939,
      "sourceSize": 89866,
      "exportedPath": "Pasted image 20240621004336.png",
      "dependencies": []
    },
    "Pasted image 20240621202105.png": {
      "modifiedTime": 1725447282939,
      "sourceSize": 54284,
      "exportedPath": "Pasted image 20240621202105.png",
      "dependencies": []
    },
    "Pasted image 20240621202300.png": {
      "modifiedTime": 1725447282939,
      "sourceSize": 69739,
      "exportedPath": "Pasted image 20240621202300.png",
      "dependencies": []
    },
    "Pasted image 20240621225105.png": {
      "modifiedTime": 1725447282939,
      "sourceSize": 80003,
      "exportedPath": "Pasted image 20240621225105.png",
      "dependencies": []
    },
    "Pasted image 20240621235412.png": {
      "modifiedTime": 1725447282939,
      "sourceSize": 34651,
      "exportedPath": "Pasted image 20240621235412.png",
      "dependencies": []
    },
    "Pasted image 20240621235423.png": {
      "modifiedTime": 1725447282939,
      "sourceSize": 13068,
      "exportedPath": "Pasted image 20240621235423.png",
      "dependencies": []
    },
    "Pasted image 20240621235442.png": {
      "modifiedTime": 1725447282939,
      "sourceSize": 18339,
      "exportedPath": "Pasted image 20240621235442.png",
      "dependencies": []
    },
    "Pasted image 20240622173336.png": {
      "modifiedTime": 1725447282939,
      "sourceSize": 37860,
      "exportedPath": "Pasted image 20240622173336.png",
      "dependencies": []
    },
    "Pasted image 20240622184349.png": {
      "modifiedTime": 1725447282939,
      "sourceSize": 10563,
      "exportedPath": "Pasted image 20240622184349.png",
      "dependencies": []
    },
    "Pasted image 20240626172127.png": {
      "modifiedTime": 1725447282939,
      "sourceSize": 44786,
      "exportedPath": "Pasted image 20240626172127.png",
      "dependencies": []
    },
    "Pasted image 20240627122402.png": {
      "modifiedTime": 1725447282939,
      "sourceSize": 199642,
      "exportedPath": "Pasted image 20240627122402.png",
      "dependencies": []
    },
    "Pasted image 20240701113218.png": {
      "modifiedTime": 1725447282939,
      "sourceSize": 5245,
      "exportedPath": "Pasted image 20240701113218.png",
      "dependencies": []
    },
    "Pasted image 20240701113320.png": {
      "modifiedTime": 1725447282939,
      "sourceSize": 5837,
      "exportedPath": "Pasted image 20240701113320.png",
      "dependencies": []
    },
    "Pasted image 20240701113546.png": {
      "modifiedTime": 1725447282939,
      "sourceSize": 47446,
      "exportedPath": "Pasted image 20240701113546.png",
      "dependencies": []
    },
    "Pasted image 20240701113614.png": {
      "modifiedTime": 1725447282939,
      "sourceSize": 25319,
      "exportedPath": "Pasted image 20240701113614.png",
      "dependencies": []
    },
    "Pasted image 20240701114143.png": {
      "modifiedTime": 1725447282939,
      "sourceSize": 13342,
      "exportedPath": "Pasted image 20240701114143.png",
      "dependencies": []
    },
    "Pasted image 20240701115336.png": {
      "modifiedTime": 1725447282939,
      "sourceSize": 46059,
      "exportedPath": "Pasted image 20240701115336.png",
      "dependencies": []
    },
    "Pasted image 20240701115810.png": {
      "modifiedTime": 1725447282939,
      "sourceSize": 71889,
      "exportedPath": "Pasted image 20240701115810.png",
      "dependencies": []
    },
    "Pasted image 20240701121329.png": {
      "modifiedTime": 1725447282939,
      "sourceSize": 82342,
      "exportedPath": "Pasted image 20240701121329.png",
      "dependencies": []
    },
    "Pasted image 20240703111509.png": {
      "modifiedTime": 1725447282939,
      "sourceSize": 4435,
      "exportedPath": "Pasted image 20240703111509.png",
      "dependencies": []
    },
    "Pasted image 20240704093411.png": {
      "modifiedTime": 1725447282939,
      "sourceSize": 25037,
      "exportedPath": "Pasted image 20240704093411.png",
      "dependencies": []
    },
    "Pasted image 20240704093611.png": {
      "modifiedTime": 1725447282939,
      "sourceSize": 25037,
      "exportedPath": "Pasted image 20240704093611.png",
      "dependencies": []
    },
    "Pasted image 20240704094056.png": {
      "modifiedTime": 1725447282939,
      "sourceSize": 108825,
      "exportedPath": "Pasted image 20240704094056.png",
      "dependencies": []
    },
    "Pasted image 20240704102602.png": {
      "modifiedTime": 1725447282939,
      "sourceSize": 49695,
      "exportedPath": "Pasted image 20240704102602.png",
      "dependencies": []
    },
    "Pasted image 20240704105532.png": {
      "modifiedTime": 1725447282939,
      "sourceSize": 741683,
      "exportedPath": "Pasted image 20240704105532.png",
      "dependencies": []
    },
    "Pasted image 20240704105544.png": {
      "modifiedTime": 1725447282939,
      "sourceSize": 741683,
      "exportedPath": "Pasted image 20240704105544.png",
      "dependencies": []
    },
    "Pasted image 20240712161013.png": {
      "modifiedTime": 1725447282939,
      "sourceSize": 21767,
      "exportedPath": "Pasted image 20240712161013.png",
      "dependencies": []
    },
    "Pasted image 20240712161207.png": {
      "modifiedTime": 1725447282939,
      "sourceSize": 21746,
      "exportedPath": "Pasted image 20240712161207.png",
      "dependencies": []
    },
    "Pasted image 20240713172639.png": {
      "modifiedTime": 1725447282939,
      "sourceSize": 55888,
      "exportedPath": "Pasted image 20240713172639.png",
      "dependencies": []
    },
    "Pasted image 20240714152942.png": {
      "modifiedTime": 1725447282939,
      "sourceSize": 91052,
      "exportedPath": "Pasted image 20240714152942.png",
      "dependencies": []
    },
    "Pasted image 20240714152959.png": {
      "modifiedTime": 1725447282939,
      "sourceSize": 122473,
      "exportedPath": "Pasted image 20240714152959.png",
      "dependencies": []
    },
    "Pasted image 20240714153112.png": {
      "modifiedTime": 1725447282939,
      "sourceSize": 82944,
      "exportedPath": "Pasted image 20240714153112.png",
      "dependencies": []
    },
    "Pasted image 20240714153200.png": {
      "modifiedTime": 1725447282939,
      "sourceSize": 34483,
      "exportedPath": "Pasted image 20240714153200.png",
      "dependencies": []
    },
    "Pasted image 20240716110652.png": {
      "modifiedTime": 1725447282939,
      "sourceSize": 0,
      "exportedPath": "Pasted image 20240716110652.png",
      "dependencies": []
    },
    "Pasted image 20240716110730.png": {
      "modifiedTime": 1725447282939,
      "sourceSize": 7299,
      "exportedPath": "Pasted image 20240716110730.png",
      "dependencies": []
    },
    "Pasted image 20240716111108.png": {
      "modifiedTime": 1725447282939,
      "sourceSize": 7299,
      "exportedPath": "Pasted image 20240716111108.png",
      "dependencies": []
    },
    "Pasted image 20240718105744.png": {
      "modifiedTime": 1725447282939,
      "sourceSize": 4346,
      "exportedPath": "Pasted image 20240718105744.png",
      "dependencies": []
    },
    "Pasted image 20240718123151.png": {
      "modifiedTime": 1725447282939,
      "sourceSize": 23057,
      "exportedPath": "Pasted image 20240718123151.png",
      "dependencies": []
    },
    "Pasted image 20240723105856.png": {
      "modifiedTime": 1725447282939,
      "sourceSize": 2543,
      "exportedPath": "Pasted image 20240723105856.png",
      "dependencies": []
    },
    "Pasted image 20240723115032.png": {
      "modifiedTime": 1725447282939,
      "sourceSize": 10739,
      "exportedPath": "Pasted image 20240723115032.png",
      "dependencies": []
    },
    "Pasted image 20240723120502.png": {
      "modifiedTime": 1725447282939,
      "sourceSize": 25536,
      "exportedPath": "Pasted image 20240723120502.png",
      "dependencies": []
    },
    "Pasted image 20240731101144.png": {
      "modifiedTime": 1725447282939,
      "sourceSize": 10973,
      "exportedPath": "Pasted image 20240731101144.png",
      "dependencies": []
    },
    "Pasted image 20240731105552.png": {
      "modifiedTime": 1725447282939,
      "sourceSize": 13034,
      "exportedPath": "Pasted image 20240731105552.png",
      "dependencies": []
    },
    "Pasted image 20240802100231.png": {
      "modifiedTime": 1725447282939,
      "sourceSize": 31199,
      "exportedPath": "Pasted image 20240802100231.png",
      "dependencies": []
    },
    "Pasted image 20240802100254.png": {
      "modifiedTime": 1725447282939,
      "sourceSize": 25964,
      "exportedPath": "Pasted image 20240802100254.png",
      "dependencies": []
    },
    "Pasted image 20240807101118.png": {
      "modifiedTime": 1725447282939,
      "sourceSize": 18252,
      "exportedPath": "Pasted image 20240807101118.png",
      "dependencies": []
    },
    "Pasted image 20240807104503.png": {
      "modifiedTime": 1725447282939,
      "sourceSize": 12266,
      "exportedPath": "Pasted image 20240807104503.png",
      "dependencies": []
    },
    "Pasted image 20240807221038.png": {
      "modifiedTime": 1725447282939,
      "sourceSize": 11703,
      "exportedPath": "Pasted image 20240807221038.png",
      "dependencies": []
    },
    "Pasted image 20240807221419.png": {
      "modifiedTime": 1725447282939,
      "sourceSize": 920,
      "exportedPath": "Pasted image 20240807221419.png",
      "dependencies": []
    },
    "Pasted image 20240808143749.png": {
      "modifiedTime": 1725447282939,
      "sourceSize": 164728,
      "exportedPath": "Pasted image 20240808143749.png",
      "dependencies": []
    },
    "Pasted image 20240808154935.png": {
      "modifiedTime": 1725447282939,
      "sourceSize": 19928,
      "exportedPath": "Pasted image 20240808154935.png",
      "dependencies": []
    },
    "Pasted image 20240809214724.png": {
      "modifiedTime": 1725447282939,
      "sourceSize": 132112,
      "exportedPath": "Pasted image 20240809214724.png",
      "dependencies": []
    },
    "Pasted image 20240813081657.png": {
      "modifiedTime": 1725447282939,
      "sourceSize": 10210,
      "exportedPath": "Pasted image 20240813081657.png",
      "dependencies": []
    },
    "Pasted image 20240814163039.png": {
      "modifiedTime": 1725447282939,
      "sourceSize": 21776,
      "exportedPath": "Pasted image 20240814163039.png",
      "dependencies": []
    },
    "Polyesters.md": {
      "modifiedTime": 1725447282939,
      "sourceSize": 598,
      "exportedPath": "Polyesters.html",
      "dependencies": []
    },
    "Polymerization.md": {
      "modifiedTime": 1725447282939,
      "sourceSize": 1463,
      "exportedPath": "Polymerization.html",
      "dependencies": []
    },
    "Polymers.md": {
      "modifiedTime": 1725447282939,
      "sourceSize": 2429,
      "exportedPath": "Polymers.html",
      "dependencies": []
    },
    "Process safety.md": {
      "modifiedTime": 1725447282939,
      "sourceSize": 736,
      "exportedPath": "Process safety.html",
      "dependencies": []
    },
    "Processing.md": {
      "modifiedTime": 1725447282939,
      "sourceSize": 5366,
      "exportedPath": "Processing.html",
      "dependencies": []
    },
    "Real Gases.md": {
      "modifiedTime": 1725447282939,
      "sourceSize": 1129,
      "exportedPath": "Real Gases.html",
      "dependencies": []
    },
    "Selection of analytical methods.md": {
      "modifiedTime": 1725447282939,
      "sourceSize": 3345,
      "exportedPath": "Selection of analytical methods.html",
      "dependencies": []
    },
    "solution to question 1.md": {
      "modifiedTime": 1725447282939,
      "sourceSize": 1997,
      "exportedPath": "solution to question 1.html",
      "dependencies": []
    },
    "Statistics problems.md": {
      "modifiedTime": 1725447282939,
      "sourceSize": 608,
      "exportedPath": "Statistics problems.html",
      "dependencies": []
    },
    "step growth.md": {
      "modifiedTime": 1725447282939,
      "sourceSize": 1124,
      "exportedPath": "step growth.html",
      "dependencies": []
    },
    "Supreme Industries.md": {
      "modifiedTime": 1725447282939,
      "sourceSize": 3971,
      "exportedPath": "Supreme Industries.html",
      "dependencies": []
    },
    "Takshil's Problem.md": {
      "modifiedTime": 1725447282939,
      "sourceSize": 1802,
      "exportedPath": "Takshil's Problem.html",
      "dependencies": []
    },
    "Types of polymers.md": {
      "modifiedTime": 1725447282939,
      "sourceSize": 5300,
      "exportedPath": "Types of polymers.html",
      "dependencies": []
    },
    "Unsteady Heat Conduction.md": {
      "modifiedTime": 1725447282939,
      "sourceSize": 2267,
      "exportedPath": "Unsteady Heat Conduction.html",
      "dependencies": []
    },
    "Volume.md": {
      "modifiedTime": 1725447282939,
      "sourceSize": 4276,
      "exportedPath": "Volume.html",
      "dependencies": []
    },
    "Water Pollution.md": {
      "modifiedTime": 1725447282939,
      "sourceSize": 4652,
      "exportedPath": "Water Pollution.html",
      "dependencies": []
    },
    "Accounts quiz 1.md": {
      "modifiedTime": 1725447282939,
      "sourceSize": 149,
      "exportedPath": "Accounts quiz 1.html",
      "dependencies": []
    },
    "Garware Hitech.md": {
      "modifiedTime": 1725447282939,
      "sourceSize": 3030,
      "exportedPath": "Garware Hitech.html",
      "dependencies": []
    },
    "Lec 8.md": {
      "modifiedTime": 1725447282939,
      "sourceSize": 2277,
      "exportedPath": "Lec 8.html",
      "dependencies": []
    },
    "Pasted image 20240821111415.png": {
      "modifiedTime": 1725447282939,
      "sourceSize": 0,
      "exportedPath": "Pasted image 20240821111415.png",
      "dependencies": []
    },
    "Pasted image 20240821111418.png": {
      "modifiedTime": 1725447282939,
      "sourceSize": 0,
      "exportedPath": "Pasted image 20240821111418.png",
      "dependencies": []
    },
    "Pasted image 20240822065437.png": {
      "modifiedTime": 1725447282939,
      "sourceSize": 23139,
      "exportedPath": "Pasted image 20240822065437.png",
      "dependencies": []
    },
    "Pasted image 20240822071834.png": {
      "modifiedTime": 1725447282939,
      "sourceSize": 4195,
      "exportedPath": "Pasted image 20240822071834.png",
      "dependencies": []
    },
    "Pasted image 20240823094343.png": {
      "modifiedTime": 1725447282939,
      "sourceSize": 60048,
      "exportedPath": "Pasted image 20240823094343.png",
      "dependencies": []
    },
    "Shaily.md": {
      "modifiedTime": 1725447282939,
      "sourceSize": 0,
      "exportedPath": "Shaily.html",
      "dependencies": []
    }
  }
}